{
  "script": {
    "steps": [],
    "maxProcessedMemTableBytes": -1,
    "columnsSelection": {
      "mode": "ALL"
    },
    "columnWidthsByName": {
      "年月日": 100,
      "年月日_parsed": 204,
      "年": 100,
      "日照時間": 100,
      "場所": 100,
      "降水量合計": 100,
      "平均気温": 100,
      "最高気温": 100,
      "最低気温": 100,
      "状況": 100,
      "開花日": 190,
      "開花日_parsed": 204,
      "年初からの日数": 100,
      "開花年": 100,
      "開花日までの日数": 100,
      "年初からの日数_暦年平均": 134
    },
    "coloring": {
      "scheme": "MEANING_AND_STATUS",
      "individualColumns": [],
      "valueColoringMode": "HASH"
    },
    "sorting": [],
    "analysisColumnData": {},
    "explorationSampling": {
      "selection": {
        "maxStoredBytes": 104857600,
        "timeout": -1,
        "filter": {
          "distinct": false,
          "enabled": false
        },
        "partitionSelectionMethod": "ALL",
        "latestPartitionsN": 1,
        "ordering": {
          "enabled": false,
          "rules": []
        },
        "samplingMethod": "HEAD_SEQUENTIAL",
        "maxRecords": 10000,
        "targetRatio": 0.02,
        "withinFirstN": -1,
        "maxReadUncompressedBytes": -1
      },
      "autoRefreshSample": false,
      "_refreshTrigger": 3
    },
    "vizSampling": {
      "autoRefreshSample": false,
      "_refreshTrigger": 0
    },
    "exploreUIParams": {
      "autoRefresh": true
    },
    "globalSearchQuery": "",
    "explorationFilters": [],
    "previewMode": "ALL_ROWS"
  },
  "charts": []
}